.gitignore
.travis.yml
AUTHORS.txt
CHANGES.txt
MANIFEST.in
README.rst
TODO.txt
development.ini
setup.cfg
setup.py
kotti_media/__init__.py
kotti_media/fanstatic.py
kotti_media/populate.py
kotti_media/resources.py
kotti_media.egg-info/PKG-INFO
kotti_media.egg-info/SOURCES.txt
kotti_media.egg-info/dependency_links.txt
kotti_media.egg-info/entry_points.txt
kotti_media.egg-info/not-zip-safe
kotti_media.egg-info/requires.txt
kotti_media.egg-info/top_level.txt
kotti_media/static/kotti_media.coffee
kotti_media/static/kotti_media.js
kotti_media/static/kotti_media.map
kotti_media/static/kotti_media.min.js
kotti_media/templates/audio-element.pt
kotti_media/templates/audio-view.pt
kotti_media/templates/edit-player-options.pt
kotti_media/templates/media-folder-view.pt
kotti_media/templates/script.pt
kotti_media/templates/video-element.pt
kotti_media/templates/video-view.pt
kotti_media/tests/browser.txt
kotti_media/tests/conftest.py
kotti_media/tests/distortion.m4a
kotti_media/tests/distortion.m4v
kotti_media/tests/distortion.mov
kotti_media/tests/distortion.mp3
kotti_media/tests/distortion.oga
kotti_media/tests/distortion.ogv
kotti_media/tests/distortion.png
kotti_media/tests/distortion.srt
kotti_media/tests/distortion.wav
kotti_media/tests/distortion.webm
kotti_media/tests/test_resources.py
kotti_media/tests/test_settings.py
kotti_media/tests/test_views.py
kotti_media/views/__init__.py
kotti_media/views/forms.py