Metadata-Version: 1.1
Name: kotti-media
Version: 0.6
Summary: Add media content to your Kotti site
Home-page: https://github.com/disko/kotti_media
Author: Andreas Kaiser
Author-email: disko@binary-punks.com
License: BSD-derived (http://www.repoze.org/LICENSE.txt)
Keywords: video audio medialementjs kotti cms pylons pyramid
Platform: UNKNOWN
Classifier: Programming Language :: Python
Classifier: Programming Language :: Python :: 2.6
Classifier: Programming Language :: Python :: 2.7
Classifier: Framework :: Pylons
Classifier: Topic :: Internet :: WWW/HTTP
Classifier: Topic :: Internet :: WWW/HTTP :: Dynamic Content
Classifier: Topic :: Internet :: WWW/HTTP :: WSGI :: Application
Classifier: License :: Repoze Public License
